[
  {
    "geographyId": "world",
    "metricId": "area",
    "classId": "world-total",
    "sketchId": null,
    "groupId": null,
    "value": 511207893395811.06
  },
  {
    "geographyId": "world",
    "metricId": "count",
    "classId": "world-total",
    "sketchId": null,
    "groupId": null,
    "value": 1
  },
  {
    "geographyId": "world",
    "metricId": "sum",
    "classId": "bo-present-surface-ph-total",
    "sketchId": null,
    "groupId": null,
    "value": 47123147.65269041
  },
  {
    "geographyId": "world",
    "metricId": "sum",
    "classId": "bo-present-surface-temp-max-total",
    "sketchId": null,
    "groupId": null,
    "value": 105908706.62344371
  },
  {
    "geographyId": "world",
    "metricId": "sum",
    "classId": "bo-present-surface-temp-min-total",
    "sketchId": null,
    "groupId": null,
    "value": 70311594.88425079
  }
]
